qbdiff/__init__.py
qbdiff/py.typed
qbdiff/__pycache__/__init__.cpython-310.pyc
qbdiff/backends/__init__.py
qbdiff/backends/__pycache__/__init__.cpython-310.pyc
qbdiff/backends/cffi/__init__.py
qbdiff/backends/cffi/_qbdiff.pyd
qbdiff/backends/cffi/build.py
qbdiff/backends/cffi/__pycache__/__init__.cpython-310.pyc
qbdiff/backends/cffi/__pycache__/build.cpython-310.pyc
qbdiff/backends/cython/__init__.py
qbdiff/backends/cython/_qbdiff.c
qbdiff/backends/cython/_qbdiff.cp310-win_amd64.pyd
qbdiff/backends/cython/_qbdiff.pyd
qbdiff/backends/cython/_qbdiff.pyi
qbdiff/backends/cython/_qbdiff.pyx
qbdiff/backends/cython/qbdiff.pxd
qbdiff/backends/cython/__pycache__/__init__.cpython-310.pyc
qbdiff-0.0.1.dist-info/METADATA
qbdiff-0.0.1.dist-info/WHEEL
qbdiff-0.0.1.dist-info/top_level.txt
qbdiff-0.0.1.dist-info/RECORD
